_foo.cpython-37m-x86_64-linux-gnu.so
tensorflow_recommenders_addons/__init__.py
tensorflow_recommenders_addons/conftest.py
tensorflow_recommenders_addons/register.py
tensorflow_recommenders_addons/version.py
tensorflow_recommenders_addons/dynamic_embedding/__init__.py
tensorflow_recommenders_addons/dynamic_embedding/core/_cuckoo_hashtable_ops.so
tensorflow_recommenders_addons/dynamic_embedding/core/_data_flow_ops.so
tensorflow_recommenders_addons/dynamic_embedding/core/_math_ops.so
tensorflow_recommenders_addons/dynamic_embedding/core/_redis_table_ops.so
tensorflow_recommenders_addons/dynamic_embedding/python/__init__.py
tensorflow_recommenders_addons/dynamic_embedding/python/keras/__init__.py
tensorflow_recommenders_addons/dynamic_embedding/python/keras/callbacks.py
tensorflow_recommenders_addons/dynamic_embedding/python/keras/models.py
tensorflow_recommenders_addons/dynamic_embedding/python/keras/layers/__init__.py
tensorflow_recommenders_addons/dynamic_embedding/python/keras/layers/embedding.py
tensorflow_recommenders_addons/dynamic_embedding/python/ops/__init__.py
tensorflow_recommenders_addons/dynamic_embedding/python/ops/cuckoo_hashtable_ops.py
tensorflow_recommenders_addons/dynamic_embedding/python/ops/data_flow_grad.py
tensorflow_recommenders_addons/dynamic_embedding/python/ops/data_flow_ops.py
tensorflow_recommenders_addons/dynamic_embedding/python/ops/distributed_embedding_variable.py
tensorflow_recommenders_addons/dynamic_embedding/python/ops/dynamic_embedding_creator.py
tensorflow_recommenders_addons/dynamic_embedding/python/ops/dynamic_embedding_ops.py
tensorflow_recommenders_addons/dynamic_embedding/python/ops/dynamic_embedding_optimizer.py
tensorflow_recommenders_addons/dynamic_embedding/python/ops/dynamic_embedding_variable.py
tensorflow_recommenders_addons/dynamic_embedding/python/ops/embedding_weights.py
tensorflow_recommenders_addons/dynamic_embedding/python/ops/hkv_hashtable_ops.py
tfra_u5-0.7.3.dist-info/LICENSE
tfra_u5-0.7.3.dist-info/METADATA
tfra_u5-0.7.3.dist-info/WHEEL
tfra_u5-0.7.3.dist-info/top_level.txt
tfra_u5-0.7.3.dist-info/RECORD
